setup.py
cuckoofilter/__init__.py
cuckoofilter/bucket.py
cuckoofilter/cuckoofilter.py
cuckoofilter/tests/__init__.py
cuckoofilter/tests/test_bucket.py
cuckoofilter/tests/test_filter.py
python_cuckoo.egg-info/PKG-INFO
python_cuckoo.egg-info/SOURCES.txt
python_cuckoo.egg-info/dependency_links.txt
python_cuckoo.egg-info/requires.txt
python_cuckoo.egg-info/top_level.txt