Metadata-Version: 1.1
Name: python-cuckoo
Version: 1.0.0
Summary: Cuckoo Filter implemenation for Python 3.x
Home-page: https://github.com/Leechael/python-cuckoo
Author: Leechael Yim
Author-email: yanleech@gmail.com
License: MIT
Download-URL: https://github.com/Leechael/python-cuckoo/tarball/1.0.0
Keywords: cuckoofilter bloomfilter
Platform: UNKNOWN
Classifier: Programming Language :: Python :: 3.4
Classifier: Programming Language :: Python :: 3.5
